[{"pk": 1172261, "verse": 1, "text": "A balan\u00e7a enganosa \u00e9 abomina\u00e7\u00e3o para o Senhor; mas o peso justo \u00e9 o seu prazer."}, {"pk": 1172262, "verse": 2, "text": "Quando vem a soberba, ent\u00e3o vem a desonra; mas com os humildes est\u00e1 a sabedoria."}, {"pk": 1172263, "verse": 3, "text": "A integridade dos retos os guia; por\u00e9m a perversidade dos desleais os destr\u00f3i."}, {"pk": 1172264, "verse": 4, "text": "De nada aproveitam as riquezas no dia da ira; por\u00e9m a justi\u00e7a livra da morte."}, {"pk": 1172265, "verse": 5, "text": "A justi\u00e7a dos perfeitos endireita o seu caminho; mas o \u00edmpio cai pela sua impiedade."}, {"pk": 1172266, "verse": 6, "text": "A justi\u00e7a dos retos os livra; mas os trai\u00e7oeiros s\u00e3o apanhados nas, suas pr\u00f3prias cobi\u00e7as."}, {"pk": 1172267, "verse": 7, "text": "Morrendo o \u00edmpio, perece a sua esperan\u00e7a; e a expectativa da iniq\u00fcidade."}, {"pk": 1172268, "verse": 8, "text": "O justo \u00e9 libertado da ang\u00fastia; e o \u00edmpio fica em seu lugar."}, {"pk": 1172269, "verse": 9, "text": "O hip\u00f3crita com a boca arru\u00edna o seu proximo; mas os justos s\u00e3o libertados pelo conhecimento."}, {"pk": 1172270, "verse": 10, "text": "Quando os justos prosperam, exulta a cidade; e quando perecem os \u00edmpios, h\u00e1 j\u00fabilo."}, {"pk": 1172271, "verse": 11, "text": "Pela b\u00ean\u00e7\u00e3o dos retos se exalta a cidade; mas pela boca dos \u00edmpios \u00e9 derrubada."}, {"pk": 1172272, "verse": 12, "text": "Quem despreza o seu pr\u00f3ximo \u00e9 falto de senso; mas o homem de entendimento se cala."}, {"pk": 1172273, "verse": 13, "text": "O que anda mexericando revela segredos; mas o fiel de esp\u00edrito encobre o neg\u00f3cio."}, {"pk": 1172274, "verse": 14, "text": "Quando n\u00e3o h\u00e1 s\u00e1bia dire\u00e7\u00e3o, o povo cai; mas na multid\u00e3o de conselheiros h\u00e1 seguran\u00e7a."}, {"pk": 1172275, "verse": 15, "text": "Decerto sofrer\u00e1 preju\u00edzo aquele que fica por fiador do estranho; mas o que aborrece a fian\u00e7a estar\u00e1 seguro."}, {"pk": 1172276, "verse": 16, "text": "A mulher apraz\u00edvel obt\u00e9m honra, e os homens violentos obt\u00eam riquezas."}, {"pk": 1172277, "verse": 17, "text": "O homem bondoso faz bem \u00e0 sua, pr\u00f3pria alma; mas o cruel faz mal a si mesmo."}, {"pk": 1172278, "verse": 18, "text": "O \u00edmpio recebe um sal\u00e1rio ilus\u00f3rio; mas o que semeia justi\u00e7a recebe galard\u00e3o seguro."}, {"pk": 1172279, "verse": 19, "text": "Quem \u00e9 fiel na retid\u00e3o encaminha, para a vida, e aquele que segue o mal encontra a morte."}, {"pk": 1172280, "verse": 20, "text": "Abomina\u00e7\u00e3o para o Senhor s\u00e3o os perversos de cora\u00e7\u00e3o; mas os que s\u00e3o perfeitos em seu caminho s\u00e3o o seu deleite."}, {"pk": 1172281, "verse": 21, "text": "Decerto o homem mau n\u00e3o ficar\u00e1 sem castigo; por\u00e9m a descend\u00eancia dos justos ser\u00e1 livre."}, {"pk": 1172282, "verse": 22, "text": "Como j\u00f3ia de ouro em focinho de porca, assim \u00e9 a mulher formosa que se aparta da discri\u00e7\u00e3o."}, {"pk": 1172283, "verse": 23, "text": "O desejo dos justos \u00e9 somente o bem; por\u00e9m a expectativa dos \u00edmpios \u00e9 a ira."}, {"pk": 1172284, "verse": 24, "text": "Um d\u00e1 liberalmente, e se torna mais rico; outro ret\u00e9m mais do que \u00e9 justo, e se empobrece."}, {"pk": 1172285, "verse": 25, "text": "A alma generosa prosperar\u00e1, e o que regar tamb\u00e9m ser\u00e1 regado."}, {"pk": 1172286, "verse": 26, "text": "Ao que ret\u00e9m o trigo o povo o amaldi\u00e7oa; mas b\u00ean\u00e7\u00e3o haver\u00e1 sobre a cabe\u00e7a do que o vende."}, {"pk": 1172287, "verse": 27, "text": "O que busca diligentemente o bem, busca favor; mas ao que procura o mal, este lhe sobrevir\u00e1."}, {"pk": 1172288, "verse": 28, "text": "Aquele que confia nas suas riquezas, cair\u00e1; mas os justos reverdecer\u00e3o como a folhagem."}, {"pk": 1172289, "verse": 29, "text": "O que perturba a sua casa herdar\u00e1 o vento; e o insensato ser\u00e1 servo do entendido de cora\u00e7\u00e3o."}, {"pk": 1172290, "verse": 30, "text": "O fruto do justo \u00e9 \u00e1rvore de vida; e o que ganha almas s\u00e1bio \u00e9."}, {"pk": 1172291, "verse": 31, "text": "Eis que o justo \u00e9 castigado na terra; quanto mais o \u00edmpio e o pecador!"}]