[{"pk": 2531813, "verse": 1, "text": "Ent\u00e3o Jesus deixou Cafarnaum e foi para a regi\u00e3o da Judeia, a leste do rio Jord\u00e3o. Mais uma vez, multid\u00f5es se juntaram ao seu redor e, como de costume, ele as ensinava."}, {"pk": 2531814, "verse": 2, "text": "Alguns fariseus vieram e tentaram apanhar Jesus numa armadilha com a seguinte pergunta: \u201cDeve-se permitir que um homem se divorcie de sua mulher?\u201d."}, {"pk": 2531815, "verse": 3, "text": "Jesus respondeu: \u201cO que Mois\u00e9s disse na lei a respeito do div\u00f3rcio?\u201d."}, {"pk": 2531816, "verse": 4, "text": "\u201cEle o permitiu\u201d, responderam os fariseus. \u201cDisse que um homem poderia dar \u00e0 esposa um certificado de div\u00f3rcio e mand\u00e1-la embora.\u201d", "comment": "Ver <a href='/NVT/5/24/1'>Dt  24.1</a>."}, {"pk": 2531817, "verse": 5, "text": "Jesus, por\u00e9m, disse: \u201cMois\u00e9s escreveu esse mandamento porque voc\u00eas t\u00eam o cora\u00e7\u00e3o duro,"}, {"pk": 2531818, "verse": 6, "text": "mas \u2018Deus os fez homem e mulher\u2019 desde o princ\u00edpio da cria\u00e7\u00e3o.", "comment": "<a href='/NVT/1/1/27'>Gn  1.27</a>; <a href='/NVT/1/5/2'>5.2</a>."}, {"pk": 2531819, "verse": 7, "text": "\u2018Por isso o homem deixa pai e m\u00e3e e se une \u00e0 sua mulher,", "comment": "Alguns manuscritos n\u00e3o trazem <em>e se une \u00e0 sua mulh</em><em>er</em>.<br><a href='/NVT/1/2/24'>Gn  2.24</a>."}, {"pk": 2531820, "verse": 8, "text": "e os dois se tornam um s\u00f3\u2019. Uma vez que j\u00e1 n\u00e3o s\u00e3o dois, mas um s\u00f3,"}, {"pk": 2531821, "verse": 9, "text": "que ningu\u00e9m separe o que Deus uniu\u201d."}, {"pk": 2531822, "verse": 10, "text": "Mais tarde, quando Jesus estava em casa com seus disc\u00edpulos, eles tocaram no assunto outra vez."}, {"pk": 2531823, "verse": 11, "text": "Jesus respondeu: \u201cQuem se divorcia de sua esposa e se casa com outra mulher comete adult\u00e9rio contra ela."}, {"pk": 2531824, "verse": 12, "text": "E, se a mulher se divorcia do marido e se casa com outro homem, comete adult\u00e9rio\u201d."}, {"pk": 2531825, "verse": 13, "text": "Certo dia, trouxeram crian\u00e7as para que Jesus pusesse as m\u00e3os sobre elas, mas os disc\u00edpulos repreendiam aqueles que as traziam."}, {"pk": 2531826, "verse": 14, "text": "Ao ver isso, Jesus ficou indignado com os disc\u00edpulos e disse: \u201cDeixem que as crian\u00e7as venham a mim. N\u00e3o as impe\u00e7am, pois o reino de Deus pertence aos que s\u00e3o como elas."}, {"pk": 2531827, "verse": 15, "text": "Eu lhes digo a verdade: quem n\u00e3o receber o reino de Deus como uma crian\u00e7a de modo algum entrar\u00e1 nele\u201d."}, {"pk": 2531828, "verse": 16, "text": "Ent\u00e3o tomou as crian\u00e7as nos bra\u00e7os, p\u00f4s as m\u00e3os sobre a cabe\u00e7a delas e as aben\u00e7oou."}, {"pk": 2531829, "verse": 17, "text": "Quando Jesus sa\u00eda para Jerusal\u00e9m, um homem veio correndo em sua dire\u00e7\u00e3o, ajoelhou-se diante dele e perguntou: \u201cBom mestre, que devo fazer para herdar a vida eterna?\u201d."}, {"pk": 2531830, "verse": 18, "text": "\u201cPor que voc\u00ea me chama de bom?\u201d, perguntou Jesus. \u201cApenas Deus \u00e9 verdadeiramente bom."}, {"pk": 2531831, "verse": 19, "text": "Voc\u00ea conhece os mandamentos: \u2018N\u00e3o mate. N\u00e3o cometa adult\u00e9rio. N\u00e3o roube. N\u00e3o d\u00ea falso testemunho. N\u00e3o engane ningu\u00e9m. Honre seu pai e sua m\u00e3e\u2019.\u201d", "comment": "<a href='/NVT/2/20/12-16'>\u00cax  20.12-16</a>; <a href='/NVT/5/5/16-20'>Dt  5.16-20</a>."}, {"pk": 2531832, "verse": 20, "text": "O homem respondeu: \u201cMestre, tenho obedecido a todos esses mandamentos desde a juventude\u201d."}, {"pk": 2531833, "verse": 21, "text": "Com amor, Jesus olhou para o homem e disse: \u201cAinda h\u00e1 uma coisa que voc\u00ea n\u00e3o fez. V\u00e1, venda todos os seus bens e d\u00ea o dinheiro aos pobres. Ent\u00e3o voc\u00ea ter\u00e1 um tesouro no c\u00e9u. Depois, venha e siga-me\u201d."}, {"pk": 2531834, "verse": 22, "text": "Ao ouvir isso, o homem ficou desapontado e foi embora triste, pois tinha muitos bens."}, {"pk": 2531835, "verse": 23, "text": "Jesus olhou ao redor e disse a seus disc\u00edpulos: \u201cComo \u00e9 dif\u00edcil os ricos entrarem no reino de Deus!\u201d."}, {"pk": 2531836, "verse": 24, "text": "Os disc\u00edpulos se admiraram de suas palavras. Mas Jesus disse outra vez: \u201cFilhos, entrar no reino de Deus \u00e9 muito dif\u00edcil.", "comment": "Alguns manuscritos acrescentam<em>para os que confiam em riquez</em><em>as</em>."}, {"pk": 2531837, "verse": 25, "text": "\u00c9 mais f\u00e1cil um camelo passar pelo buraco de uma agulha que um rico entrar no reino de Deus\u201d."}, {"pk": 2531838, "verse": 26, "text": "Perplexos, os disc\u00edpulos perguntaram: \u201cEnt\u00e3o quem pode ser salvo?\u201d."}, {"pk": 2531839, "verse": 27, "text": "Jesus olhou atentamente para eles e respondeu: \u201cPara as pessoas isso \u00e9 imposs\u00edvel, mas n\u00e3o para Deus. Para Deus, tudo \u00e9 poss\u00edvel\u201d."}, {"pk": 2531840, "verse": 28, "text": "Ent\u00e3o Pedro come\u00e7ou a falar: \u201cDeixamos tudo para segui-lo\u201d."}, {"pk": 2531841, "verse": 29, "text": "Jesus respondeu: \u201cEu lhes garanto que todos que deixaram casa, irm\u00e3os, irm\u00e3s, m\u00e3e, pai, filhos ou propriedades por minha causa e por causa das boas-novas"}, {"pk": 2531842, "verse": 30, "text": "receber\u00e3o em troca, neste mundo, cem vezes mais casas, irm\u00e3os, irm\u00e3s, m\u00e3es, filhos e propriedades, com persegui\u00e7\u00e3o, e, no mundo futuro, ter\u00e3o a vida eterna."}, {"pk": 2531843, "verse": 31, "text": "Contudo, muitos primeiros ser\u00e3o os \u00faltimos, e muitos \u00faltimos ser\u00e3o os primeiros\u201d."}, {"pk": 2531844, "verse": 32, "text": "Por esse tempo, subiam para Jerusal\u00e9m, e Jesus ia \u00e0 frente. Os disc\u00edpulos estavam muito admirados, e o povo que os seguia tinha grande temor. Jesus chamou os Doze \u00e0 parte e, mais uma vez, come\u00e7ou a descrever tudo que estava prestes a lhe acontecer."}, {"pk": 2531845, "verse": 33, "text": "\u201cOu\u00e7am\u201d, disse ele. \u201cEstamos subindo para Jerusal\u00e9m, onde o Filho do Homem ser\u00e1 tra\u00eddo e entregue aos principais sacerdotes e aos mestres da lei. Eles o condenar\u00e3o \u00e0 morte e o entregar\u00e3o aos gentios."}, {"pk": 2531846, "verse": 34, "text": "Zombar\u00e3o dele, cuspir\u00e3o nele, o a\u00e7oitar\u00e3o e o matar\u00e3o, mas depois de tr\u00eas dias ele ressuscitar\u00e1.\u201d"}, {"pk": 2531847, "verse": 35, "text": "Ent\u00e3o Tiago e Jo\u00e3o, filhos de Zebedeu, vieram e falaram com ele: \u201cMestre, queremos que nos fa\u00e7a um favor\u201d."}, {"pk": 2531848, "verse": 36, "text": "\u201cQue favor \u00e9 esse?\u201d, perguntou ele."}, {"pk": 2531849, "verse": 37, "text": "Eles responderam: \u201cQuando o senhor se sentar em seu trono glorioso, queremos nos sentar em lugares de honra ao seu lado, um \u00e0 sua direita e outro \u00e0 sua esquerda\u201d."}, {"pk": 2531850, "verse": 38, "text": "Jesus lhes disse: \u201cVoc\u00eas n\u00e3o sabem o que est\u00e3o pedindo! S\u00e3o capazes de beber do c\u00e1lice que beberei? S\u00e3o capazes de ser batizados com o batismo com que serei batizado?\u201d."}, {"pk": 2531851, "verse": 39, "text": "\u201cSomos!\u201d, responderam eles. Ent\u00e3o Jesus disse: \u201cDe fato, voc\u00eas beber\u00e3o do meu c\u00e1lice e ser\u00e3o batizados com o meu batismo."}, {"pk": 2531852, "verse": 40, "text": "N\u00e3o cabe a mim, no entanto, dizer quem se sentar\u00e1 \u00e0 minha direita ou \u00e0 minha esquerda. Esses lugares ser\u00e3o daqueles para quem eles foram preparados\u201d."}, {"pk": 2531853, "verse": 41, "text": "Quando os outros dez disc\u00edpulos ouviram o que Tiago e Jo\u00e3o haviam pedido, ficaram indignados."}, {"pk": 2531854, "verse": 42, "text": "Ent\u00e3o Jesus os reuniu e disse: \u201cVoc\u00eas sabem que os que s\u00e3o considerados l\u00edderes neste mundo t\u00eam poder sobre o povo, e que os oficiais exercem sua autoridade sobre os s\u00faditos."}, {"pk": 2531855, "verse": 43, "text": "Entre voc\u00eas, por\u00e9m, ser\u00e1 diferente. Quem quiser ser o l\u00edder entre voc\u00eas, que seja servo,"}, {"pk": 2531856, "verse": 44, "text": "e quem quiser ser o primeiro entre voc\u00eas, que se torne escravo de todos."}, {"pk": 2531857, "verse": 45, "text": "Pois nem mesmo o Filho do Homem veio para ser servido, mas para servir e dar sua vida em resgate por muitos\u201d."}, {"pk": 2531858, "verse": 46, "text": "Ent\u00e3o chegaram a Jeric\u00f3. Quando Jesus e seus disc\u00edpulos sa\u00edam da cidade, uma grande multid\u00e3o os seguiu. Um mendigo cego chamado Bartimeu, filho de Timeu, estava sentado \u00e0 beira do caminho."}, {"pk": 2531859, "verse": 47, "text": "Quando Bartimeu soube que Jesus de Nazar\u00e9 estava perto, come\u00e7ou a gritar: \u201cJesus, Filho de Davi, tenha miseric\u00f3rdia de mim!\u201d."}, {"pk": 2531860, "verse": 48, "text": "Muitos lhe diziam aos brados: \u201cCale-se!\u201d. Ele, por\u00e9m, gritava ainda mais alto: \u201cFilho de Davi, tenha miseric\u00f3rdia de mim!\u201d."}, {"pk": 2531861, "verse": 49, "text": "Quando Jesus o ouviu, parou e disse: \u201cFalem para ele vir aqui\u201d. Ent\u00e3o chamaram o cego. \u201cAnime-se!\u201d, disseram. \u201cVenha, ele o est\u00e1 chamando!\u201d"}, {"pk": 2531862, "verse": 50, "text": "Bartimeu jogou sua capa para o lado, levantou-se de um salto e foi at\u00e9 Jesus."}, {"pk": 2531863, "verse": 51, "text": "\u201cO que voc\u00ea quer que eu lhe fa\u00e7a?\u201d, perguntou Jesus. O cego respondeu: \u201cRabi, quero enxergar\u201d.", "comment": "O texto grego usa o termo hebraico <em>Rab</em><em>oni.</em>"}, {"pk": 2531864, "verse": 52, "text": "Jesus lhe disse: \u201cV\u00e1, pois sua f\u00e9 o curou\u201d. No mesmo instante, o homem passou a ver e seguiu Jesus pelo caminho."}]