[{"pk": 2529465, "verse": 1, "text": "\u201cQuando Israel era menino, eu o amei,<br> e do Egito chamei meu filho.<br>"}, {"pk": 2529466, "verse": 2, "text": "Mas, quanto mais o chamava,<br> mais ele se afastava de mim;<br> oferecia sacrif\u00edcios \u00e0s imagens de Baal<br> e queimava incenso aos \u00eddolos.<br>", "comment": "Conforme a Septuaginta; o hebraico traz <em>quanto mais eles o chamavam, mais ele se afastava de</em><em>les</em>."}, {"pk": 2529467, "verse": 3, "text": "Ensinei Israel a andar,<br> conduzindo-o pela m\u00e3o.<br> Mas ele n\u00e3o se deu conta<br> de que era eu quem dele cuidava.<br>", "comment": "Em hebraico, <em>Efraim</em>, refer\u00eancia a Israel, o reino do norte; tamb\u00e9m em <a href='/NVT/28/11/8'>11.8</a>,<a href='/NVT/28/11/9'>9</a>,<a href='/NVT/28/11/12'>12</a>."}, {"pk": 2529468, "verse": 4, "text": "Guiei Israel<br> com meus la\u00e7os de amor.<br> Tirei o jugo de seu pesco\u00e7o<br> e eu mesmo me inclinei para aliment\u00e1-lo.<br>"}, {"pk": 2529469, "verse": 5, "text": "\u201cMas, porque meu povo n\u00e3o quer voltar para mim,<br> voltar\u00e1 para o Egito<br> e ser\u00e1 obrigado a viver na Ass\u00edria.<br>"}, {"pk": 2529470, "verse": 6, "text": "A guerra devastar\u00e1 suas cidades,<br> e os inimigos derrubar\u00e3o suas portas.<br> Destruir\u00e3o os israelitas,<br> por causa de suas tramas.<br>"}, {"pk": 2529471, "verse": 7, "text": "Pois meu povo est\u00e1 decidido a me abandonar;<br> eles me chamam Alt\u00edssimo,<br> mas n\u00e3o me honram de verdade.<br>"}, {"pk": 2529472, "verse": 8, "text": "\u201cComo eu poderia desistir de voc\u00ea, Israel?<br> Como poderia deix\u00e1-lo?<br> Como poderia destru\u00ed-lo como Adm\u00e1<br> ou arras\u00e1-lo como Zeboim?<br> Meu cora\u00e7\u00e3o est\u00e1 dilacerado,<br> e minha compaix\u00e3o transborda.<br>"}, {"pk": 2529473, "verse": 9, "text": "N\u00e3o enviarei minha ira furiosa,<br> n\u00e3o destruirei Israel,<br> pois sou Deus, e n\u00e3o um simples mortal.<br> Sou o Santo que vive entre voc\u00eas,<br> e n\u00e3o virei com minha ira.<br>"}, {"pk": 2529474, "verse": 10, "text": "Pois, um dia, meu povo me seguir\u00e1;<br> eu, o SENHOR, rugirei como le\u00e3o,<br> e, quando eu rugir,<br> meu povo retornar\u00e1, tremendo, desde o oeste.<br>"}, {"pk": 2529475, "verse": 11, "text": "Como um bando de aves, vir\u00e3o do Egito;<br> tremendo como pombas, voltar\u00e3o da Ass\u00edria.<br> Eu os trarei de volta para casa\u201d,<br> diz o SENHOR.<br>"}, {"pk": 2529476, "verse": 12, "text": "Israel me cerca de mentiras e trai\u00e7\u00f5es,<br> mas Jud\u00e1 ainda obedece a Deus<br> e \u00e9 fiel ao Santo.<br>", "comment": "No texto hebraico, o vers\u00edculo <a href='/NVT/28/11/12'>11.12</a> \u00e9 numerado <a href='/NVT/28/12/1'>12.1</a>.<br>Ou <em>e Jud\u00e1 \u00e9 rebelde contra Deus, o Santo fiel</em>. O significado do hebraico \u00e9 incerto."}]