[{"pk": 3304411, "verse": 1, "text": "Job continued his discourse:"}, {"pk": 3304412, "verse": 2, "text": "\u201cHow I long for the months gone by, for the days when God watched over me,"}, {"pk": 3304413, "verse": 3, "text": "when his lamp shone on my head and by his light I walked through darkness!"}, {"pk": 3304414, "verse": 4, "text": "Oh, for the days when I was in my prime, when God\u2019s intimate friendship blessed my house,"}, {"pk": 3304415, "verse": 5, "text": "when the Almighty was still with me and my children were around me,"}, {"pk": 3304416, "verse": 6, "text": "when my path was drenched with cream and the rock poured out for me streams of olive oil. "}, {"pk": 3304417, "verse": 7, "text": "\u201cWhen I went to the gate of the city and took my seat in the public square,"}, {"pk": 3304418, "verse": 8, "text": "the young men saw me and stepped aside and the old men rose to their feet;"}, {"pk": 3304419, "verse": 9, "text": "the chief men refrained from speaking and covered their mouths with their hands;"}, {"pk": 3304420, "verse": 10, "text": "the voices of the nobles were hushed, and their tongues stuck to the roof of their mouths."}, {"pk": 3304421, "verse": 11, "text": "Whoever heard me spoke well of me, and those who saw me commended me,"}, {"pk": 3304422, "verse": 12, "text": "because I rescued the poor who cried for help, and the fatherless who had none to assist them."}, {"pk": 3304423, "verse": 13, "text": "The one who was dying blessed me; I made the widow\u2019s heart sing."}, {"pk": 3304424, "verse": 14, "text": "I put on righteousness as my clothing; justice was my robe and my turban."}, {"pk": 3304425, "verse": 15, "text": "I was eyes to the blind and feet to the lame."}, {"pk": 3304426, "verse": 16, "text": "I was a father to the needy; I took up the case of the stranger."}, {"pk": 3304427, "verse": 17, "text": "I broke the fangs of the wicked and snatched the victims from their teeth. "}, {"pk": 3304428, "verse": 18, "text": "\u201cI thought, \u2018I will die in my own house, my days as numerous as the grains of sand."}, {"pk": 3304429, "verse": 19, "text": "My roots will reach to the water, and the dew will lie all night on my branches."}, {"pk": 3304430, "verse": 20, "text": "My glory will not fade; the bow will be ever new in my hand.\u2019 "}, {"pk": 3304431, "verse": 21, "text": "\u201cPeople listened to me expectantly, waiting in silence for my counsel."}, {"pk": 3304432, "verse": 22, "text": "After I had spoken, they spoke no more; my words fell gently on their ears."}, {"pk": 3304433, "verse": 23, "text": "They waited for me as for showers and drank in my words as the spring rain."}, {"pk": 3304434, "verse": 24, "text": "When I smiled at them, they scarcely believed it; the light of my face was precious to them.", "comment": "The meaning of the Hebrew for this clause is uncertain."}, {"pk": 3304435, "verse": 25, "text": "I chose the way for them and sat as their chief; I dwelt as a king among his troops; I was like one who comforts mourners."}]