[{"pk": 4468591, "verse": 1, "text": "<b><font size=-1>C\u00e2ntico dos degraus</font>.</b> MUITAS vezes me angustiaram desde a minha mocidade, diga agora Israel;"}, {"pk": 4468592, "verse": 2, "text": "Muitas vezes me angustiaram desde a minha mocidade; todavia n\u00e3o prevaleceram contra mim."}, {"pk": 4468593, "verse": 3, "text": "Os lavradores araram sobre as minhas costas; compridos fizeram os seus sulcos."}, {"pk": 4468594, "verse": 4, "text": "O S<font size=-1>ENHOR</font> <i>\u00e9</i> justo; cortou as cordas dos \u00edmpios."}, {"pk": 4468595, "verse": 5, "text": "Sejam confundidos, e voltem para tr\u00e1s todos os que odeiam a Si\u00e3o."}, {"pk": 4468596, "verse": 6, "text": "Sejam como a erva dos telhados que se seca antes que <i>a</i> arranquem."}, {"pk": 4468597, "verse": 7, "text": "Com a qual o segador n\u00e3o enche a sua m\u00e3o, nem o que ata os feixes <i>enche</i> o seu bra\u00e7o."}, {"pk": 4468598, "verse": 8, "text": "Nem tampouco os que passam dizem: A b\u00ean\u00e7\u00e3o do S<font size=-1>ENHOR</font> <i>seja</i> sobre v\u00f3s; n\u00f3s vos aben\u00e7oamos em nome do S<font size=-1>ENHOR</font>."}]