[{"pk": 3796051, "verse": 1, "text": "Jesus, cheio do Esp\u00edrito Santo, voltou do Jord\u00e3o e foi guiado pelo mesmo Esp\u00edrito, no deserto,"}, {"pk": 3796052, "verse": 2, "text": "durante quarenta dias, sendo tentado pelo diabo. Nada comeu naqueles dias, ao fim dos quais teve fome."}, {"pk": 3796053, "verse": 3, "text": "Ent\u00e3o o diabo disse a Jesus: \u2014 Se voc\u00ea \u00e9 o Filho de Deus, mande que esta pedra se transforme em p\u00e3o."}, {"pk": 3796054, "verse": 4, "text": "Mas Jesus lhe respondeu: \u2014 Est\u00e1 escrito: \u201cO ser humano n\u00e3o viver\u00e1 s\u00f3 de p\u00e3o.\u201d<sup>\u24df</sup> ", "comment": "\u24df <a href='/NAA/5/8/3'>Dt 8.3</a>"}, {"pk": 3796055, "verse": 5, "text": "Ent\u00e3o o diabo o levou para um lugar mais alto e num instante lhe mostrou todos os reinos do mundo."}, {"pk": 3796056, "verse": 6, "text": "E disse: \u2014 Eu lhe darei todo este poder e a gl\u00f3ria destes reinos, porque isso me foi entregue, e posso dar a quem eu quiser."}, {"pk": 3796057, "verse": 7, "text": "Portanto, se voc\u00ea me adorar, tudo isso ser\u00e1 seu."}, {"pk": 3796058, "verse": 8, "text": "Mas Jesus respondeu: \u2014 Est\u00e1 escrito: \u201cAdore o Senhor, seu Deus,<br> e preste culto somente a ele.\u201d<sup>\u24e0</sup><br>", "comment": "\u24e0 <a href='/NAA/5/6/13'>Dt 6.13</a>"}, {"pk": 3796059, "verse": 9, "text": "Ent\u00e3o o diabo levou Jesus a Jerusal\u00e9m, colocou-o sobre o pin\u00e1culo<sup>[3]</sup> do templo e disse: \u2014 Se voc\u00ea \u00e9 o Filho de Deus, jogue-se daqui,", "comment": "[3] O lugar mais alto"}, {"pk": 3796060, "verse": 10, "text": "porque est\u00e1 escrito: \u201cAos seus anjos ele dar\u00e1 ordens<br> a seu respeito,<br> para que o guardem.\u201d<sup>\u24e1</sup><br>", "comment": "\u24e1 <a href='/NAA/19/91/11'>Sl 91.11</a>"}, {"pk": 3796061, "verse": 11, "text": "E: \u201cEles o sustentar\u00e3o nas suas m\u00e3os,<br> para que voc\u00ea n\u00e3o tropece<br> em alguma pedra.\u201d<sup>\u24e2</sup><br>", "comment": "\u24e2 <a href='/NAA/19/91/12'>Sl 91.12</a>"}, {"pk": 3796062, "verse": 12, "text": "Jesus respondeu ao diabo: \u2014 Tamb\u00e9m foi dito: \u201cN\u00e3o ponha \u00e0 prova o Senhor, seu Deus.\u201d<sup>\u24e3</sup> ", "comment": "\u24e3 <a href='/NAA/5/6/16'>Dt 6.16</a>"}, {"pk": 3796063, "verse": 13, "text": "Tendo conclu\u00eddo todas as tenta\u00e7\u00f5es, o diabo afastou-se de Jesus, at\u00e9 momento oportuno.<sup>\u24e4</sup> ", "comment": "\u24e4 <a href='/NAA/42/22/3'>Lc 22.3</a>,<a href='/NAA/42/22/53'>53</a>"}, {"pk": 3796064, "verse": 14, "text": "Ent\u00e3o Jesus, no poder do Esp\u00edrito, voltou para a Galileia, e a sua fama correu por toda aquela regi\u00e3o."}, {"pk": 3796065, "verse": 15, "text": "E ensinava nas sinagogas, sendo elogiado por todos."}, {"pk": 3796066, "verse": 16, "text": "Jesus foi para Nazar\u00e9, onde havia sido criado. Num s\u00e1bado, entrou na sinagoga, segundo o seu costume, e levantou-se para ler."}, {"pk": 3796067, "verse": 17, "text": "Ent\u00e3o lhe deram o livro do profeta Isa\u00edas. E, abrindo o livro, achou o lugar onde est\u00e1 escrito:"}, {"pk": 3796068, "verse": 18, "text": "\u201cO Esp\u00edrito do Senhor<br> est\u00e1 sobre mim,<br> porque ele me ungiu<br> para evangelizar os pobres;<br> enviou-me para proclamar<br> liberta\u00e7\u00e3o aos cativos<br> e restaura\u00e7\u00e3o da vista aos cegos,<br> para p\u00f4r em liberdade<br> os oprimidos,<br>"}, {"pk": 3796069, "verse": 19, "text": "e proclamar o ano aceit\u00e1vel<br> do Senhor.\u201d<sup>\u24e5</sup><br>", "comment": "\u24e5 <a href='/NAA/23/61/1-2'>Is 61.1-2</a>"}, {"pk": 3796070, "verse": 20, "text": "Tendo fechado o livro, Jesus o devolveu ao assistente e sentou-se. Todos na sinagoga tinham os olhos fixos nele."}, {"pk": 3796071, "verse": 21, "text": "Ent\u00e3o Jesus come\u00e7ou a dizer: \u2014 Hoje se cumpriu a Escritura que voc\u00eas acabam de ouvir."}, {"pk": 3796072, "verse": 22, "text": "Todos davam testemunho dele e se maravilhavam das palavras cheias de gra\u00e7a que lhe sa\u00edam dos l\u00e1bios. E perguntavam: \u2014 N\u00e3o \u00e9 este o filho de Jos\u00e9?"}, {"pk": 3796073, "verse": 23, "text": "Ent\u00e3o Jesus disse: \u2014 Sem d\u00favida, voc\u00eas citar\u00e3o para mim o prov\u00e9rbio: \u201cM\u00e9dico, cure-se a si mesmo.\u201d Dir\u00e3o: \u201cTudo o que ouvimos que voc\u00ea fez em Cafarnaum, fa\u00e7a-o tamb\u00e9m aqui na sua terra.\u201d"}, {"pk": 3796074, "verse": 24, "text": "E Jesus prosseguiu: \u2014 De fato, afirmo a voc\u00eas que nenhum profeta \u00e9 bem recebido na sua pr\u00f3pria terra.<sup>\u24e6</sup> ", "comment": "\u24e6 <a href='/NAA/43/4/44'>Jo 4.44</a>"}, {"pk": 3796075, "verse": 25, "text": "Na verdade lhes digo que havia muitas vi\u00favas em Israel no tempo de Elias, quando o c\u00e9u se fechou<sup>\u24e7</sup> por tr\u00eas anos e seis meses, reinando grande fome em toda a terra,", "comment": "\u24e7 <a href='/NAA/11/17/1'>1Rs 17.1</a>"}, {"pk": 3796076, "verse": 26, "text": "e Elias n\u00e3o foi enviado a nenhuma delas, a n\u00e3o ser a uma vi\u00fava de Sarepta<sup>\u24e8</sup> de Sidom.", "comment": "\u24e8 <a href='/NAA/11/17/8-16'>1Rs 17.8-16</a>"}, {"pk": 3796077, "verse": 27, "text": "Havia tamb\u00e9m muitos leprosos em Israel nos dias do profeta Eliseu, e nenhum deles foi purificado, a n\u00e3o ser Naam\u00e3, o s\u00edrio.<sup>\u24e9</sup> ", "comment": "\u24e9 <a href='/NAA/12/5/1-14'>2Rs 5.1-14</a>"}, {"pk": 3796078, "verse": 28, "text": "Todos na sinagoga, ouvindo estas coisas, se encheram de ira."}, {"pk": 3796079, "verse": 29, "text": "E, levantando-se, expulsaram Jesus da cidade e o levaram at\u00e9 o alto do monte sobre o qual a cidade estava edificada, para que, de l\u00e1, pudessem atir\u00e1-lo abaixo."}, {"pk": 3796080, "verse": 30, "text": "Jesus, por\u00e9m, passando pelo meio deles, foi embora.<sup>\u24d0</sup> ", "comment": "\u24d0 <a href='/NAA/43/8/59'>Jo 8.59</a>; <a href='/NAA/43/10/39'>10.39</a>"}, {"pk": 3796081, "verse": 31, "text": "E Jesus foi a Cafarnaum, cidade da Galileia, e os ensinava no s\u00e1bado."}, {"pk": 3796082, "verse": 32, "text": "E maravilhavam-se com a sua doutrina,<sup>\u24d1</sup> porque a sua palavra era com autoridade.", "comment": "\u24d1 <a href='/NAA/40/7/28-29'>Mt 7.28-29</a>"}, {"pk": 3796083, "verse": 33, "text": "E apareceu na sinagoga um homem possu\u00eddo de um esp\u00edrito de dem\u00f4nio imundo, o qual gritou em alta voz:"}, {"pk": 3796084, "verse": 34, "text": "\u2014 Ah! O que voc\u00ea quer conosco, Jesus Nazareno? Voc\u00ea veio para nos destruir? Sei muito bem quem voc\u00ea \u00e9: o Santo de Deus!"}, {"pk": 3796085, "verse": 35, "text": "Mas Jesus o repreendeu, dizendo: \u2014 Cale-se e saia desse homem. O dem\u00f4nio, depois de o ter jogado no ch\u00e3o no meio de todos, saiu daquele homem sem lhe fazer mal."}, {"pk": 3796086, "verse": 36, "text": "Todos ficaram admirados e comentavam entre si: \u2014 Que palavra \u00e9 esta? Pois, com autoridade e poder, ele ordena aos esp\u00edritos imundos, e eles saem."}, {"pk": 3796087, "verse": 37, "text": "E a fama de Jesus se espalhava por todos os lugares daquela regi\u00e3o."}, {"pk": 3796088, "verse": 38, "text": "Deixando a sinagoga, Jesus foi para a casa de Sim\u00e3o. A sogra de Sim\u00e3o estava doente, com febre muito alta, e pediram a Jesus em favor dela."}, {"pk": 3796089, "verse": 39, "text": "E inclinando-se para ela, Jesus repreendeu a febre, e esta a deixou. E imediatamente ela se levantou e passou a servi-los."}, {"pk": 3796090, "verse": 40, "text": "Ao p\u00f4r do sol, todos os que tinham enfermos, com diferentes tipos de doen\u00e7a, os trouxeram a Jesus. E ele os curava, impondo as m\u00e3os sobre cada um deles."}, {"pk": 3796091, "verse": 41, "text": "Tamb\u00e9m de muitos sa\u00edam dem\u00f4nios, gritando e dizendo: \u2014 Voc\u00ea \u00e9 o Filho de Deus!<sup>\u24d2</sup> Ele, por\u00e9m, os repreendia para que n\u00e3o falassem, pois sabiam que ele era o Cristo.", "comment": "\u24d2 <a href='/NAA/41/3/11'>Mc 3.11</a>"}, {"pk": 3796092, "verse": 42, "text": "Quando amanheceu, Jesus saiu e foi para um lugar deserto. As multid\u00f5es o procuravam, foram at\u00e9 junto dele e n\u00e3o queriam deixar que ele fosse embora."}, {"pk": 3796093, "verse": 43, "text": "Jesus, por\u00e9m, lhes disse: \u2014 \u00c9 necess\u00e1rio que eu anuncie o evangelho do Reino de Deus tamb\u00e9m nas outras cidades, pois \u00e9 para isso que fui enviado."}, {"pk": 3796094, "verse": 44, "text": "E pregava nas sinagogas da Judeia.<sup>\u24d3</sup> ", "comment": "\u24d3 <a href='/NAA/40/4/23'>Mt 4.23</a>; <a href='/NAA/40/9/35'>9.35</a>"}]