[{"pk": 1459350, "verse": 1, "text": "Oh Dios,  da tus juicios al rey,<br> Y tu justicia al hijo del rey."}, {"pk": 1459351, "verse": 2, "text": "El juzgar\u00e1 a tu pueblo con justicia,<br> Y a tus afligidos con juicio."}, {"pk": 1459352, "verse": 3, "text": "Los montes llevar\u00e1n paz al pueblo,<br> Y los collados justicia."}, {"pk": 1459353, "verse": 4, "text": "Juzgar\u00e1 a los afligidos del pueblo,<br> Salvar\u00e1 a los hijos del menesteroso,<br> Y aplastar\u00e1 al opresor."}, {"pk": 1459354, "verse": 5, "text": "Te temer\u00e1n mientras duren el sol<br> Y la luna,  de generaci\u00f3n en generaci\u00f3n."}, {"pk": 1459355, "verse": 6, "text": "Descender\u00e1 como la lluvia sobre la hierba cortada;<br> Como el roc\u00edo que destila sobre la tierra."}, {"pk": 1459356, "verse": 7, "text": "Florecer\u00e1 en sus d\u00edas justicia,<br> Y muchedumbre de paz,  hasta que no haya luna."}, {"pk": 1459357, "verse": 8, "text": "Dominar\u00e1 de mar a mar,<br> Y desde el r\u00edo hasta los confines de la tierra.", "comment": "<a href='/RV1960/38/9/10'>Zac. 9.10</a>."}, {"pk": 1459358, "verse": 9, "text": "Ante \u00e9l se postrar\u00e1n los moradores del desierto,<br> Y sus enemigos lamer\u00e1n el polvo."}, {"pk": 1459359, "verse": 10, "text": "Los reyes de Tarsis y de las costas traer\u00e1n presentes;<br> Los reyes de Sab\u00e1 y de Seba ofrecer\u00e1n dones."}, {"pk": 1459360, "verse": 11, "text": "Todos los reyes se postrar\u00e1n delante de \u00e9l;<br> Todas las naciones le servir\u00e1n."}, {"pk": 1459361, "verse": 12, "text": "Porque \u00e9l librar\u00e1 al menesteroso que clamare,<br> Y al afligido que no tuviere quien le socorra."}, {"pk": 1459362, "verse": 13, "text": "Tendr\u00e1 misericordia del pobre y del menesteroso,<br> Y salvar\u00e1 la vida de los pobres."}, {"pk": 1459363, "verse": 14, "text": "De enga\u00f1o y de violencia redimir\u00e1 sus almas,<br> Y la sangre de ellos ser\u00e1 preciosa ante sus ojos."}, {"pk": 1459364, "verse": 15, "text": "Vivir\u00e1,  y se le dar\u00e1 del oro de Sab\u00e1,<br> Y se orar\u00e1 por \u00e9l continuamente;<br> Todo el d\u00eda se le bendecir\u00e1."}, {"pk": 1459365, "verse": 16, "text": "Ser\u00e1 echado un pu\u00f1ado de grano en la tierra,  en las cumbres de los montes;<br> Su fruto har\u00e1 ruido como el L\u00edbano,<br> Y los de la ciudad florecer\u00e1n como la hierba de la tierra."}, {"pk": 1459366, "verse": 17, "text": "Ser\u00e1 su nombre para siempre,<br> Se perpetuar\u00e1 su nombre mientras dure el sol.<br> Benditas ser\u00e1n en \u00e9l todas las naciones;<br> Lo llamar\u00e1n bienaventurado."}, {"pk": 1459367, "verse": 18, "text": "Bendito Jehov\u00e1 Dios,  el Dios de Israel,<br> El \u00fanico que hace maravillas."}, {"pk": 1459368, "verse": 19, "text": "Bendito su nombre glorioso para siempre,<br> Y toda la tierra sea llena de su gloria.<br> Am\u00e9n y Am\u00e9n."}, {"pk": 1459369, "verse": 20, "text": "Aqu\u00ed terminan las oraciones de David,  hijo de Isa\u00ed."}]